{"head":[{"path":"/items/armors/skkeenmort/","fileName":"skkeenmort.head","name":"skkeenmorthead","shortdescription":"Mortimer Helmet","icon":"icons.png:head","maleFrames":"head.png","femaleFrames":"head.png","mask":"mask.png","colorOptions":[{"#ffca8a":"696969","#e0975c":"444444","#a85636":"2a2a2a","#6f2919":"000000"},{"#ffca8a":"838383","#e0975c":"555555","#a85636":"383838","#6f2919":"151515"},{"#ffca8a":"b5b5b5","#e0975c":"808080","#a85636":"555555","#6f2919":"303030"},{"#ffca8a":"e6e6e6","#e0975c":"b6b6b6","#a85636":"7b7b7b","#6f2919":"373737"},{"#ffca8a":"f4988c","#e0975c":"d93a3a","#a85636":"932625","#6f2919":"601119"},{"#ffca8a":"ffd495","#e0975c":"ea9931","#a85636":"af4e00","#6f2919":"6e2900"},{"#ffca8a":"ffffa7","#e0975c":"e2c344","#a85636":"a46e06","#6f2919":"642f00"},{"#ffca8a":"b2e89d","#e0975c":"51bd3b","#a85636":"247824","#6f2919":"144216"},{"#ffca8a":"96cbe7","#e0975c":"5588d4","#a85636":"344495","#6f2919":"1a1c51"},{"#ffca8a":"d29ce7","#e0975c":"a451c4","#a85636":"6a2284","#6f2919":"320c40"},{"#ffca8a":"eab3db","#e0975c":"d35eae","#a85636":"97276d","#6f2919":"59163f"},{"#ffca8a":"ccae7c","#e0975c":"a47844","#a85636":"754c23","#6f2919":"472b13"}]},{"path":"/items/armors/skkeenclass/","fileName":"skkeenclass.head","name":"skkeenclasshead","shortdescription":"Keen Helmet","icon":"icons.png:head","maleFrames":"head.png","femaleFrames":"head.png","mask":"mask.png","colorOptions":[{"#ffca8a":"ffffa9","#e0975c":"fcfc54","#a85636":"d1a629","#6f2919":"a85400"},{"#ffca8a":"838383","#e0975c":"555555","#a85636":"383838","#6f2919":"151515"},{"#ffca8a":"b5b5b5","#e0975c":"808080","#a85636":"555555","#6f2919":"303030"},{"#ffca8a":"e6e6e6","#e0975c":"b6b6b6","#a85636":"7b7b7b","#6f2919":"373737"},{"#ffca8a":"f4988c","#e0975c":"d93a3a","#a85636":"932625","#6f2919":"601119"},{"#ffca8a":"ffd495","#e0975c":"ea9931","#a85636":"af4e00","#6f2919":"6e2900"},{"#ffca8a":"ffffa7","#e0975c":"e2c344","#a85636":"a46e06","#6f2919":"642f00"},{"#ffca8a":"b2e89d","#e0975c":"51bd3b","#a85636":"247824","#6f2919":"144216"},{"#ffca8a":"96cbe7","#e0975c":"5588d4","#a85636":"344495","#6f2919":"1a1c51"},{"#ffca8a":"d29ce7","#e0975c":"a451c4","#a85636":"6a2284","#6f2919":"320c40"},{"#ffca8a":"eab3db","#e0975c":"d35eae","#a85636":"97276d","#6f2919":"59163f"},{"#ffca8a":"ccae7c","#e0975c":"a47844","#a85636":"754c23","#6f2919":"472b13"}]},{"path":"/items/armors/skkeenclass2/","fileName":"skkeenclass2.head","name":"skkeenclass2head","shortdescription":"Keen Helmet 2","icon":"icons.png:head","maleFrames":"head.png","femaleFrames":"head.png","mask":"mask.png","colorOptions":[{"#ffca8a":"ffffa9","#e0975c":"fcfc54","#a85636":"d1a629","#6f2919":"a85400"},{"#ffca8a":"838383","#e0975c":"555555","#a85636":"383838","#6f2919":"151515"},{"#ffca8a":"b5b5b5","#e0975c":"808080","#a85636":"555555","#6f2919":"303030"},{"#ffca8a":"e6e6e6","#e0975c":"b6b6b6","#a85636":"7b7b7b","#6f2919":"373737"},{"#ffca8a":"f4988c","#e0975c":"d93a3a","#a85636":"932625","#6f2919":"601119"},{"#ffca8a":"ffd495","#e0975c":"ea9931","#a85636":"af4e00","#6f2919":"6e2900"},{"#ffca8a":"ffffa7","#e0975c":"e2c344","#a85636":"a46e06","#6f2919":"642f00"},{"#ffca8a":"b2e89d","#e0975c":"51bd3b","#a85636":"247824","#6f2919":"144216"},{"#ffca8a":"96cbe7","#e0975c":"5588d4","#a85636":"344495","#6f2919":"1a1c51"},{"#ffca8a":"d29ce7","#e0975c":"a451c4","#a85636":"6a2284","#6f2919":"320c40"},{"#ffca8a":"eab3db","#e0975c":"d35eae","#a85636":"97276d","#6f2919":"59163f"},{"#ffca8a":"ccae7c","#e0975c":"a47844","#a85636":"754c23","#6f2919":"472b13"}]},{"path":"/items/armors/skkeenmort2/","fileName":"skkeenmort2.head","name":"skkeenmort2head","shortdescription":"Mortimer Helmet 2","icon":"icons.png:head","maleFrames":"head.png","femaleFrames":"head.png","mask":"mask.png","colorOptions":[{"#ffca8a":"696969","#e0975c":"444444","#a85636":"2a2a2a","#6f2919":"000000"},{"#ffca8a":"838383","#e0975c":"555555","#a85636":"383838","#6f2919":"151515"},{"#ffca8a":"b5b5b5","#e0975c":"808080","#a85636":"555555","#6f2919":"303030"},{"#ffca8a":"e6e6e6","#e0975c":"b6b6b6","#a85636":"7b7b7b","#6f2919":"373737"},{"#ffca8a":"f4988c","#e0975c":"d93a3a","#a85636":"932625","#6f2919":"601119"},{"#ffca8a":"ffd495","#e0975c":"ea9931","#a85636":"af4e00","#6f2919":"6e2900"},{"#ffca8a":"ffffa7","#e0975c":"e2c344","#a85636":"a46e06","#6f2919":"642f00"},{"#ffca8a":"b2e89d","#e0975c":"51bd3b","#a85636":"247824","#6f2919":"144216"},{"#ffca8a":"96cbe7","#e0975c":"5588d4","#a85636":"344495","#6f2919":"1a1c51"},{"#ffca8a":"d29ce7","#e0975c":"a451c4","#a85636":"6a2284","#6f2919":"320c40"},{"#ffca8a":"eab3db","#e0975c":"d35eae","#a85636":"97276d","#6f2919":"59163f"},{"#ffca8a":"ccae7c","#e0975c":"a47844","#a85636":"754c23","#6f2919":"472b13"}]},{"path":"/items/armors/skkeenscuba/","fileName":"skkeenscuba.head","name":"skkeenscubahead","shortdescription":"Scuba Mask","icon":"icons.png:head","maleFrames":"head.png","femaleFrames":"head.png","mask":"mask.png","colorOptions":[{"#ffca8a":"7d7d7d","#e0975c":"545454","#a85636":"323232","#6f2919":"000000"},{"#ffca8a":"838383","#e0975c":"555555","#a85636":"383838","#6f2919":"151515"},{"#ffca8a":"b5b5b5","#e0975c":"808080","#a85636":"555555","#6f2919":"303030"},{"#ffca8a":"e6e6e6","#e0975c":"b6b6b6","#a85636":"7b7b7b","#6f2919":"373737"},{"#ffca8a":"f4988c","#e0975c":"d93a3a","#a85636":"932625","#6f2919":"601119"},{"#ffca8a":"ffd495","#e0975c":"ea9931","#a85636":"af4e00","#6f2919":"6e2900"},{"#ffca8a":"ffffa7","#e0975c":"e2c344","#a85636":"a46e06","#6f2919":"642f00"},{"#ffca8a":"b2e89d","#e0975c":"51bd3b","#a85636":"247824","#6f2919":"144216"},{"#ffca8a":"96cbe7","#e0975c":"5588d4","#a85636":"344495","#6f2919":"1a1c51"},{"#ffca8a":"d29ce7","#e0975c":"a451c4","#a85636":"6a2284","#6f2919":"320c40"},{"#ffca8a":"eab3db","#e0975c":"d35eae","#a85636":"97276d","#6f2919":"59163f"},{"#ffca8a":"ccae7c","#e0975c":"a47844","#a85636":"754c23","#6f2919":"472b13"}]}],"chest":[{"path":"/items/armors/skkeenscuba/","fileName":"skkeenscuba.chest","name":"skkeenscubachest","shortdescription":"Scuba Top","icon":"icons.png:chest","maleFrames":{"body":"chestm.png","backSleeve":"bsleeve.png","frontSleeve":"fsleeve.png"},"femaleFrames":{"body":"chestf.png","backSleeve":"bsleeve.png","frontSleeve":"fsleeve.png"},"colorOptions":[{"#ffca8a":"7d7d7d","#e0975c":"545454","#a85636":"323232","#6f2919":"000000"},{"#ffca8a":"838383","#e0975c":"555555","#a85636":"383838","#6f2919":"151515"},{"#ffca8a":"b5b5b5","#e0975c":"808080","#a85636":"555555","#6f2919":"303030"},{"#ffca8a":"e6e6e6","#e0975c":"b6b6b6","#a85636":"7b7b7b","#6f2919":"373737"},{"#ffca8a":"f4988c","#e0975c":"d93a3a","#a85636":"932625","#6f2919":"601119"},{"#ffca8a":"ffd495","#e0975c":"ea9931","#a85636":"af4e00","#6f2919":"6e2900"},{"#ffca8a":"ffffa7","#e0975c":"e2c344","#a85636":"a46e06","#6f2919":"642f00"},{"#ffca8a":"b2e89d","#e0975c":"51bd3b","#a85636":"247824","#6f2919":"144216"},{"#ffca8a":"96cbe7","#e0975c":"5588d4","#a85636":"344495","#6f2919":"1a1c51"},{"#ffca8a":"d29ce7","#e0975c":"a451c4","#a85636":"6a2284","#6f2919":"320c40"},{"#ffca8a":"eab3db","#e0975c":"d35eae","#a85636":"97276d","#6f2919":"59163f"},{"#ffca8a":"ccae7c","#e0975c":"a47844","#a85636":"754c23","#6f2919":"472b13"}]},{"path":"/items/armors/skkeenpj/","fileName":"skkeenpj.chest","name":"skkeenpjchest","shortdescription":"Keen PJ Top","icon":"icons.png:chest","maleFrames":{"body":"chestm.png","backSleeve":"bsleeve.png","frontSleeve":"fsleeve.png"},"femaleFrames":{"body":"chestf.png","backSleeve":"bsleeve.png","frontSleeve":"fsleeve.png"},"colorOptions":[{"#ffca8a":"b1ffff","#e0975c":"54fcfc","#a85636":"00a8a8","#6f2919":"008383"},{"#ffca8a":"838383","#e0975c":"555555","#a85636":"383838","#6f2919":"151515"},{"#ffca8a":"b5b5b5","#e0975c":"808080","#a85636":"555555","#6f2919":"303030"},{"#ffca8a":"e6e6e6","#e0975c":"b6b6b6","#a85636":"7b7b7b","#6f2919":"373737"},{"#ffca8a":"f4988c","#e0975c":"d93a3a","#a85636":"932625","#6f2919":"601119"},{"#ffca8a":"ffd495","#e0975c":"ea9931","#a85636":"af4e00","#6f2919":"6e2900"},{"#ffca8a":"ffffa7","#e0975c":"e2c344","#a85636":"a46e06","#6f2919":"642f00"},{"#ffca8a":"b2e89d","#e0975c":"51bd3b","#a85636":"247824","#6f2919":"144216"},{"#ffca8a":"96cbe7","#e0975c":"5588d4","#a85636":"344495","#6f2919":"1a1c51"},{"#ffca8a":"d29ce7","#e0975c":"a451c4","#a85636":"6a2284","#6f2919":"320c40"},{"#ffca8a":"eab3db","#e0975c":"d35eae","#a85636":"97276d","#6f2919":"59163f"},{"#ffca8a":"ccae7c","#e0975c":"a47844","#a85636":"754c23","#6f2919":"472b13"}]},{"path":"/items/armors/skkeenclass/","fileName":"skkeenclass.chest","name":"skkeenclasschest","shortdescription":"Keen Shirt","icon":"icons.png:chest","maleFrames":{"body":"chestm.png","backSleeve":"bsleeve.png","frontSleeve":"fsleeve.png"},"femaleFrames":{"body":"chestf.png","backSleeve":"bsleeve.png","frontSleeve":"fsleeve.png"},"colorOptions":[{"#ffca8a":"fa9efa","#e0975c":"fc54fc","#a85636":"a800a8","#6f2919":"890189"},{"#ffca8a":"838383","#e0975c":"555555","#a85636":"383838","#6f2919":"151515"},{"#ffca8a":"b5b5b5","#e0975c":"808080","#a85636":"555555","#6f2919":"303030"},{"#ffca8a":"e6e6e6","#e0975c":"b6b6b6","#a85636":"7b7b7b","#6f2919":"373737"},{"#ffca8a":"f4988c","#e0975c":"d93a3a","#a85636":"932625","#6f2919":"601119"},{"#ffca8a":"ffd495","#e0975c":"ea9931","#a85636":"af4e00","#6f2919":"6e2900"},{"#ffca8a":"ffffa7","#e0975c":"e2c344","#a85636":"a46e06","#6f2919":"642f00"},{"#ffca8a":"b2e89d","#e0975c":"51bd3b","#a85636":"247824","#6f2919":"144216"},{"#ffca8a":"96cbe7","#e0975c":"5588d4","#a85636":"344495","#6f2919":"1a1c51"},{"#ffca8a":"d29ce7","#e0975c":"a451c4","#a85636":"6a2284","#6f2919":"320c40"},{"#ffca8a":"eab3db","#e0975c":"d35eae","#a85636":"97276d","#6f2919":"59163f"},{"#ffca8a":"ccae7c","#e0975c":"a47844","#a85636":"754c23","#6f2919":"472b13"}]},{"path":"/items/armors/skkeenmort/","fileName":"skkeenmort.chest","name":"skkeenmortchest","shortdescription":"Mortimer Shirt","icon":"icons.png:chest","maleFrames":{"body":"chestm.png","backSleeve":"bsleeve.png","frontSleeve":"fsleeve.png"},"femaleFrames":{"body":"chestf.png","backSleeve":"bsleeve.png","frontSleeve":"fsleeve.png"},"colorOptions":[{"#ffca8a":"ffabab","#e0975c":"fc5454","#a85636":"a80000","#6f2919":"840000"},{"#ffca8a":"838383","#e0975c":"555555","#a85636":"383838","#6f2919":"151515"},{"#ffca8a":"b5b5b5","#e0975c":"808080","#a85636":"555555","#6f2919":"303030"},{"#ffca8a":"e6e6e6","#e0975c":"b6b6b6","#a85636":"7b7b7b","#6f2919":"373737"},{"#ffca8a":"f4988c","#e0975c":"d93a3a","#a85636":"932625","#6f2919":"601119"},{"#ffca8a":"ffd495","#e0975c":"ea9931","#a85636":"af4e00","#6f2919":"6e2900"},{"#ffca8a":"ffffa7","#e0975c":"e2c344","#a85636":"a46e06","#6f2919":"642f00"},{"#ffca8a":"b2e89d","#e0975c":"51bd3b","#a85636":"247824","#6f2919":"144216"},{"#ffca8a":"96cbe7","#e0975c":"5588d4","#a85636":"344495","#6f2919":"1a1c51"},{"#ffca8a":"d29ce7","#e0975c":"a451c4","#a85636":"6a2284","#6f2919":"320c40"},{"#ffca8a":"eab3db","#e0975c":"d35eae","#a85636":"97276d","#6f2919":"59163f"},{"#ffca8a":"ccae7c","#e0975c":"a47844","#a85636":"754c23","#6f2919":"472b13"}]}],"legs":[{"path":"/items/armors/skkeenclass/","fileName":"skkeenclass.legs","name":"skkeenclasslegs","shortdescription":"Keen Jeans","icon":"icons.png:pants","maleFrames":"pants.png","femaleFrames":"pants.png","colorOptions":[{"#ffca8a":"80ccf7","#e0975c":"30aff7","#a85636":"2d61de","#6f2919":"0725aa"},{"#ffca8a":"838383","#e0975c":"555555","#a85636":"383838","#6f2919":"151515"},{"#ffca8a":"b5b5b5","#e0975c":"808080","#a85636":"555555","#6f2919":"303030"},{"#ffca8a":"e6e6e6","#e0975c":"b6b6b6","#a85636":"7b7b7b","#6f2919":"373737"},{"#ffca8a":"f4988c","#e0975c":"d93a3a","#a85636":"932625","#6f2919":"601119"},{"#ffca8a":"ffd495","#e0975c":"ea9931","#a85636":"af4e00","#6f2919":"6e2900"},{"#ffca8a":"ffffa7","#e0975c":"e2c344","#a85636":"a46e06","#6f2919":"642f00"},{"#ffca8a":"b2e89d","#e0975c":"51bd3b","#a85636":"247824","#6f2919":"144216"},{"#ffca8a":"96cbe7","#e0975c":"5588d4","#a85636":"344495","#6f2919":"1a1c51"},{"#ffca8a":"d29ce7","#e0975c":"a451c4","#a85636":"6a2284","#6f2919":"320c40"},{"#ffca8a":"eab3db","#e0975c":"d35eae","#a85636":"97276d","#6f2919":"59163f"},{"#ffca8a":"ccae7c","#e0975c":"a47844","#a85636":"754c23","#6f2919":"472b13"}]},{"path":"/items/armors/skkeenmort/","fileName":"skkeenmort.legs","name":"skkeenmortlegs","shortdescription":"Mortimer Jeans","icon":"icons.png:pants","maleFrames":"pants.png","femaleFrames":"pants.png","colorOptions":[{"#ffca8a":"696969","#e0975c":"444444","#a85636":"2a2a2a","#6f2919":"000000"},{"#ffca8a":"838383","#e0975c":"555555","#a85636":"383838","#6f2919":"151515"},{"#ffca8a":"b5b5b5","#e0975c":"808080","#a85636":"555555","#6f2919":"303030"},{"#ffca8a":"e6e6e6","#e0975c":"b6b6b6","#a85636":"7b7b7b","#6f2919":"373737"},{"#ffca8a":"f4988c","#e0975c":"d93a3a","#a85636":"932625","#6f2919":"601119"},{"#ffca8a":"ffd495","#e0975c":"ea9931","#a85636":"af4e00","#6f2919":"6e2900"},{"#ffca8a":"ffffa7","#e0975c":"e2c344","#a85636":"a46e06","#6f2919":"642f00"},{"#ffca8a":"b2e89d","#e0975c":"51bd3b","#a85636":"247824","#6f2919":"144216"},{"#ffca8a":"96cbe7","#e0975c":"5588d4","#a85636":"344495","#6f2919":"1a1c51"},{"#ffca8a":"d29ce7","#e0975c":"a451c4","#a85636":"6a2284","#6f2919":"320c40"},{"#ffca8a":"eab3db","#e0975c":"d35eae","#a85636":"97276d","#6f2919":"59163f"},{"#ffca8a":"ccae7c","#e0975c":"a47844","#a85636":"754c23","#6f2919":"472b13"}]},{"path":"/items/armors/skkeenpj/","fileName":"skkeenpj.legs","name":"skkeenpjlegs","shortdescription":"Keen PJ Pants","icon":"icons.png:pants","maleFrames":"pants.png","femaleFrames":"pants.png","colorOptions":[{"#ffca8a":"b1ffff","#e0975c":"54fcfc","#a85636":"00a8a8","#6f2919":"008383"},{"#ffca8a":"838383","#e0975c":"555555","#a85636":"383838","#6f2919":"151515"},{"#ffca8a":"b5b5b5","#e0975c":"808080","#a85636":"555555","#6f2919":"303030"},{"#ffca8a":"e6e6e6","#e0975c":"b6b6b6","#a85636":"7b7b7b","#6f2919":"373737"},{"#ffca8a":"f4988c","#e0975c":"d93a3a","#a85636":"932625","#6f2919":"601119"},{"#ffca8a":"ffd495","#e0975c":"ea9931","#a85636":"af4e00","#6f2919":"6e2900"},{"#ffca8a":"ffffa7","#e0975c":"e2c344","#a85636":"a46e06","#6f2919":"642f00"},{"#ffca8a":"b2e89d","#e0975c":"51bd3b","#a85636":"247824","#6f2919":"144216"},{"#ffca8a":"96cbe7","#e0975c":"5588d4","#a85636":"344495","#6f2919":"1a1c51"},{"#ffca8a":"d29ce7","#e0975c":"a451c4","#a85636":"6a2284","#6f2919":"320c40"},{"#ffca8a":"eab3db","#e0975c":"d35eae","#a85636":"97276d","#6f2919":"59163f"},{"#ffca8a":"ccae7c","#e0975c":"a47844","#a85636":"754c23","#6f2919":"472b13"}]},{"path":"/items/armors/skkeenscuba/","fileName":"skkeenscuba.legs","name":"skkeenscubalegs","shortdescription":"Scuba Pants","icon":"icons.png:pants","maleFrames":"pants.png","femaleFrames":"pants.png","colorOptions":[{"#ffca8a":"7d7d7d","#e0975c":"545454","#a85636":"323232","#6f2919":"000000"},{"#ffca8a":"838383","#e0975c":"555555","#a85636":"383838","#6f2919":"151515"},{"#ffca8a":"b5b5b5","#e0975c":"808080","#a85636":"555555","#6f2919":"303030"},{"#ffca8a":"e6e6e6","#e0975c":"b6b6b6","#a85636":"7b7b7b","#6f2919":"373737"},{"#ffca8a":"f4988c","#e0975c":"d93a3a","#a85636":"932625","#6f2919":"601119"},{"#ffca8a":"ffd495","#e0975c":"ea9931","#a85636":"af4e00","#6f2919":"6e2900"},{"#ffca8a":"ffffa7","#e0975c":"e2c344","#a85636":"a46e06","#6f2919":"642f00"},{"#ffca8a":"b2e89d","#e0975c":"51bd3b","#a85636":"247824","#6f2919":"144216"},{"#ffca8a":"96cbe7","#e0975c":"5588d4","#a85636":"344495","#6f2919":"1a1c51"},{"#ffca8a":"d29ce7","#e0975c":"a451c4","#a85636":"6a2284","#6f2919":"320c40"},{"#ffca8a":"eab3db","#e0975c":"d35eae","#a85636":"97276d","#6f2919":"59163f"},{"#ffca8a":"ccae7c","#e0975c":"a47844","#a85636":"754c23","#6f2919":"472b13"}]}],"back":[]}